luna/__init__.py
luna/featurevis/__init__.py
luna/featurevis/featurevis.py
luna/featurevis/image_reader.py
luna/featurevis/images.py
luna/featurevis/relu_grad.py
luna/featurevis/transformations.py
luna/pretrained_models/__init__.py
luna/pretrained_models/googlenet.py
luna/pretrained_models/models.py
luna_fviz-0.1.dist-info/LICENSE.md
luna_fviz-0.1.dist-info/METADATA
luna_fviz-0.1.dist-info/WHEEL
luna_fviz-0.1.dist-info/top_level.txt
luna_fviz-0.1.dist-info/RECORD
