Metadata-Version: 2.1
Name: luna-fviz
Version: 0.1
Summary: Feature Visualization with Tensorflow 2
Home-page: https://github.com/Sparkier/luna
Author: Alex Bäuerle
Author-email: alex.baeuerle@uni-ulm.de
License: UNKNOWN
Platform: UNKNOWN
Classifier: Programming Language :: Python :: 3
Classifier: License :: OSI Approved :: MIT License
Classifier: Operating System :: OS Independent
Requires-Python: >=3.6
License-File: LICENSE.md
Requires-Dist: tensorflow
Requires-Dist: tf-slim
Requires-Dist: keras
Requires-Dist: numpy
